shinychat/__init__.py
shinychat/__version.py
shinychat/_chat.py
shinychat/_chat_bookmark.py
shinychat/_chat_normalize.py
shinychat/_chat_normalize_chatlas.py
shinychat/_chat_provider_types.py
shinychat/_chat_tokenizer.py
shinychat/_chat_types.py
shinychat/_html_deps_py_shiny.py
shinychat/_markdown_stream.py
shinychat/_typing_extensions.py
shinychat/_utils.py
shinychat/py.typed
shinychat/express/__init__.py
shinychat/playwright/__init__.py
shinychat/playwright/_chat.py
shinychat/types/__init__.py
shinychat/www/GIT_VERSION
shinychat/www/chat/chat.css
shinychat/www/chat/chat.css.map
shinychat/www/chat/chat.js
shinychat/www/chat/chat.js.map
shinychat/www/markdown-stream/markdown-stream.css
shinychat/www/markdown-stream/markdown-stream.css.map
shinychat/www/markdown-stream/markdown-stream.js
shinychat/www/markdown-stream/markdown-stream.js.map
shinychat-0.2.7.dist-info/METADATA
shinychat-0.2.7.dist-info/WHEEL
shinychat-0.2.7.dist-info/licenses/LICENSE
shinychat-0.2.7.dist-info/RECORD
